setup.py
django_form_models.egg-info/PKG-INFO
django_form_models.egg-info/SOURCES.txt
django_form_models.egg-info/dependency_links.txt
django_form_models.egg-info/requires.txt
django_form_models.egg-info/top_level.txt
form_models/__init__.py
form_models/admin.py
form_models/fields.py
form_models/models.py
form_models/views.py
form_models/tests/__init__.py
form_models/tests/factories.py
form_models/tests/run.py
form_models/tests/test_form_models.py
form_models/tests/tools.py