Metadata-Version: 1.0
Name: django-form-models
Version: 0.2.0
Summary: Sample models for modelling django forms and fields, and integrate with crispy forms layout.
Home-page: http://incuna.com/
Author: Incuna Ltd
Author-email: admin@incuna.com
License: UNKNOWN
Platform: UNKNOWN
